{
  "alpinevpn": {
    "commit_message": "Sync with upstream (hotio/base@alpinevpn) and apply custom updates",
    "commit_sha": "95d866e8ee586a2a93751727e2b58043e59814c5",
    "description": "Alpine 3.23",
    "last_updated": "2026-05-24T11:36:48.000Z",
    "last_updated_url": "https://github.com/engels74/base-image/actions/runs/26360164206",
    "tags": [
      "",
      "alpinevpn",
      "alpinevpn-95d866e",
      "",
      "",
      "",
      ""
    ]
  },
  "noblevpn": {
    "commit_message": "Sync with upstream (hotio/base@noblevpn) and apply custom updates",
    "commit_sha": "d49c883d4dc2090e9964a98998f6f100a9a287dc",
    "description": "Ubuntu 24.04",
    "last_updated": "2026-05-24T11:43:43.000Z",
    "last_updated_url": "https://github.com/engels74/base-image/actions/runs/26360307229",
    "tags": [
      "",
      "noblevpn",
      "noblevpn-d49c883",
      "",
      "",
      "",
      ""
    ]
  }
}
