{
  "legacy": {
    "commit_message": "Upstream update: alpinevpn-4dcfd96 => alpinevpn-213d573",
    "commit_sha": "177c180dddf463793ebf94730428f3ddcc159c0b",
    "description": "Fixed to v4.3.9",
    "hide": false,
    "last_updated": "2026-01-12T07:21:37.000Z",
    "last_updated_url": "https://github.com/engels74/qbittorrent/actions/runs/20911151619",
    "latest": false,
    "tags": [
      "legacy",
      "legacy-4.3.9",
      "legacy-177c180",
      "legacy-v4",
      "legacy-v4.3",
      "legacy-v4.3.9"
    ]
  },
  "release": {
    "commit_message": "Upstream update: alpinevpn-89f692c => alpinevpn-dc8231b",
    "commit_sha": "61122a36e6f521993c972dfa64e76b5c10c9e6a9",
    "description": "Releases",
    "hide": false,
    "last_updated": "2026-01-12T22:13:43.000Z",
    "last_updated_url": "https://github.com/engels74/qbittorrent/actions/runs/20936842127",
    "latest": true,
    "tags": [
      "latest",
      "release",
      "release-61122a3",
      "release-5.1.4",
      "release-v5",
      "release-v5.1",
      "release-v5.1.4"
    ]
  }
}
