{
  "nightly": {
    "commit_message": "Version, Upstream or Packages update",
    "commit_sha": "7dd7df3f40b010f658bfdf00c13351a6e2705572",
    "description": "nightly",
    "last_updated": "2026-05-15T14:29:49.000Z",
    "last_updated_url": "https://github.com/engels74/qflood/actions/runs/25923349375",
    "tags": [
      "",
      "nightly",
      "nightly-7dd7df3",
      "nightly-5.2.0--25919415228",
      "nightly-v5",
      "nightly-v5.2",
      "nightly-v5.2.0"
    ]
  },
  "release": {
    "commit_message": "Version, Upstream or Packages update",
    "commit_sha": "9f5258b2a4a2927db2736b88b594f5e057c25606",
    "description": "Releases",
    "last_updated": "2026-05-15T14:29:47.000Z",
    "last_updated_url": "https://github.com/engels74/qflood/actions/runs/25923347920",
    "tags": [
      "latest",
      "release",
      "release-9f5258b",
      "release-5.2.0--4.14.1",
      "release-v5",
      "release-v5.2",
      "release-v5.2.0"
    ]
  }
}
