{
  "nightly": {
    "commit_message": "Modified: meta.json",
    "commit_sha": "2b293f55892156a6edaa79837128fb6c6fb30451",
    "description": "nightly",
    "last_updated": "2026-07-23T14:05:02.000Z",
    "last_updated_url": "https://github.com/engels74/qflood/actions/runs/30014156071",
    "tags": [
      "",
      "nightly",
      "nightly-2b293f5",
      "nightly-5.2.3--30011132168",
      "nightly-v5",
      "nightly-v5.2",
      "nightly-v5.2.3"
    ]
  },
  "release": {
    "commit_message": "Modified: meta.json",
    "commit_sha": "2d90dca32f8f6970c8ac535f296ec13c3542119d",
    "description": "Releases",
    "last_updated": "2026-07-16T15:41:06.000Z",
    "last_updated_url": "https://github.com/engels74/qflood/actions/runs/29512269224",
    "tags": [
      "latest",
      "release",
      "release-2d90dca",
      "release-5.2.3--4.15.0",
      "release-v5",
      "release-v5.2",
      "release-v5.2.3"
    ]
  }
}
