{
  "nightly": {
    "commit_message": "Standardize to hotio naming convention\n\n- Rename flood_version to version_flood\n- Update Dockerfile ARG names accordingly\n- Remove UDP ports from WEBUI_PORTS (TCP only)",
    "commit_sha": "d1a01975ce145df3b88aee280c2e71752d38cd54",
    "description": "nightly",
    "hide": false,
    "last_updated": "2026-01-14T22:12:57.000Z",
    "last_updated_url": "https://github.com/engels74/qflood/actions/runs/21011748851",
    "latest": false,
    "tags": [
      "",
      "nightly",
      "nightly-d1a0197",
      "nightly-5.1.4--20486217775",
      "nightly-v5",
      "nightly-v5.1",
      "nightly-v5.1.4"
    ]
  },
  "release": {
    "commit_message": "refactor: align with upstream hotio patterns\n\n- Rewrite forwarded_port_update_app to restart-based approach\n- Add VPN port forwarding wait logic to service-qbittorrent\n- Remove default qBittorrent.conf (qBittorrent handles internally)\n- Use bash-functions and log_inf for consistent logging\n- Use cleaner ${LIBTORRENT//v/} parameter expansion",
    "commit_sha": "6d6386588cf5962594df3f3da0c5b6936e806a13",
    "description": "Releases",
    "hide": false,
    "last_updated": "2026-01-15T09:31:54.000Z",
    "last_updated_url": "https://github.com/engels74/qflood/actions/runs/21026381983",
    "latest": true,
    "tags": [
      "latest",
      "release",
      "release-6d63865",
      "release-5.1.4--4.11.0",
      "release-v5",
      "release-v5.1",
      "release-v5.1.4"
    ]
  }
}
