{
  "nightly": {
    "commit_message": "Modified: meta.json",
    "commit_sha": "b2a5aa60e247a76b7c2219434e43f72fa09f8f13",
    "description": "nightly",
    "last_updated": "2026-07-09T15:57:45.000Z",
    "last_updated_url": "https://github.com/engels74/qflood/actions/runs/29031589220",
    "tags": [
      "",
      "nightly",
      "nightly-b2a5aa6",
      "nightly-5.2.3--29028734210",
      "nightly-v5",
      "nightly-v5.2",
      "nightly-v5.2.3"
    ]
  },
  "release": {
    "commit_message": "Modified: meta.json",
    "commit_sha": "b982ca3ac35ef9b08c8423e805bf82f003d26320",
    "description": "Releases",
    "last_updated": "2026-07-08T22:12:25.000Z",
    "last_updated_url": "https://github.com/engels74/qflood/actions/runs/28979359128",
    "tags": [
      "latest",
      "release",
      "release-b982ca3",
      "release-5.2.3--4.14.3",
      "release-v5",
      "release-v5.2",
      "release-v5.2.3"
    ]
  }
}
