{
  "nightly": {
    "commit_message": "Version update: 2d6880cff34f33e1bbd57f10673be873f3ca4589 => dbd71a37866d0864b409b3ff5c7e34553899e62f",
    "commit_sha": "b95b976e1674c07f1ed0c531000c6f59c0db5f00",
    "description": "Every commit to develop",
    "last_updated": "2026-04-06T21:00:25.000Z",
    "last_updated_url": "https://github.com/engels74/sabnzbd/actions/runs/24051034846",
    "tags": [
      "",
      "nightly",
      "nightly-b95b976",
      "nightly-dbd71a37866d0864b409b3ff5c7e34553899e62f",
      "",
      "",
      ""
    ]
  },
  "release": {
    "commit_message": "Upstream update: alpinevpn-6d5cbf5 => alpinevpn-167fa4e",
    "commit_sha": "33f5e7fdb3b3bca2cd7dbbb9774a5a7f05b0882d",
    "description": "Releases",
    "last_updated": "2026-02-25T21:28:58.000Z",
    "last_updated_url": "https://github.com/engels74/sabnzbd/actions/runs/22416724225",
    "tags": [
      "latest",
      "release",
      "release-33f5e7f",
      "release-4.5.5",
      "release-v4",
      "release-v4.5",
      "release-v4.5.5"
    ]
  },
  "testing": {
    "commit_message": "Upstream update: alpinevpn-6d5cbf5 => alpinevpn-167fa4e",
    "commit_sha": "ea619d52d293907d9b72038e1dff39f72d870f2e",
    "description": "Pre-releases",
    "last_updated": "2026-02-25T21:28:59.000Z",
    "last_updated_url": "https://github.com/engels74/sabnzbd/actions/runs/22416724984",
    "tags": [
      "",
      "testing",
      "testing-ea619d5",
      "testing-4.5.5",
      "testing-v4",
      "testing-v4.5",
      "testing-v4.5.5"
    ]
  }
}
