{
  "nightly": {
    "commit_message": "Modified: meta.json",
    "commit_sha": "925b21cd5547f9fbdae5ddf74cfa9ed623f8743c",
    "description": "Every commit to develop",
    "last_updated": "2026-07-16T07:23:57.000Z",
    "last_updated_url": "https://github.com/engels74/sabnzbd/actions/runs/29479792202",
    "tags": [
      "",
      "nightly",
      "nightly-925b21c",
      "nightly-5b7a89ffb8a9287046e2fb02a803861f2db83369",
      "",
      "",
      ""
    ]
  },
  "release": {
    "commit_message": "fix: move user bundle markers to user-bundles.d for s6-overlay >= 3.2.3.1",
    "commit_sha": "22b6fafa41c0542d04f69e85ff0d1141ea314f3d",
    "description": "Releases",
    "last_updated": "2026-07-15T14:41:34.000Z",
    "last_updated_url": "https://github.com/engels74/sabnzbd/actions/runs/29424697585",
    "tags": [
      "latest",
      "release",
      "release-22b6faf",
      "release-5.0.4",
      "release-v5",
      "release-v5.0",
      "release-v5.0.4"
    ]
  },
  "testing": {
    "commit_message": "fix: move user bundle markers to user-bundles.d for s6-overlay >= 3.2.3.1",
    "commit_sha": "1e4ca177af138b56d90a850f38d042d76b5b9471",
    "description": "Pre-releases",
    "last_updated": "2026-07-15T14:41:38.000Z",
    "last_updated_url": "https://github.com/engels74/sabnzbd/actions/runs/29424701638",
    "tags": [
      "",
      "testing",
      "testing-1e4ca17",
      "testing-5.0.4",
      "testing-v5",
      "testing-v5.0",
      "testing-v5.0.4"
    ]
  }
}
