{
  "nightly": {
    "commit_message": "Version update: 5025f9ec5d8fb2aa41b277f299543e3f42b321b3 => e40098d0e7f1a88d1eb87271033dbf1141f17089",
    "commit_sha": "bbf61f074704d910f11cf35581aa7386f0e4ba98",
    "description": "Every commit to develop",
    "last_updated": "2026-02-02T10:05:03.000Z",
    "last_updated_url": "https://github.com/engels74/sabnzbd/actions/runs/21585711234",
    "tags": [
      "",
      "nightly",
      "nightly-bbf61f0",
      "nightly-e40098d0e7f1a88d1eb87271033dbf1141f17089",
      "",
      "",
      ""
    ]
  },
  "release": {
    "commit_message": "Upstream update: alpinevpn-a8c5f31 => alpinevpn-6d5cbf5",
    "commit_sha": "2bf7455ca506aeb132cea7493e58ea81d09b301f",
    "description": "Releases",
    "last_updated": "2026-01-29T07:35:38.000Z",
    "last_updated_url": "https://github.com/engels74/sabnzbd/actions/runs/21469645114",
    "tags": [
      "latest",
      "release",
      "release-2bf7455",
      "release-4.5.5",
      "release-v4",
      "release-v4.5",
      "release-v4.5.5"
    ]
  },
  "testing": {
    "commit_message": "Upstream update: alpinevpn-a8c5f31 => alpinevpn-6d5cbf5",
    "commit_sha": "045581e27148697ee96df4505fa3abe854471819",
    "description": "Pre-releases",
    "last_updated": "2026-01-29T07:35:39.000Z",
    "last_updated_url": "https://github.com/engels74/sabnzbd/actions/runs/21469645621",
    "tags": [
      "",
      "testing",
      "testing-045581e",
      "testing-4.5.5",
      "testing-v4",
      "testing-v4.5",
      "testing-v4.5.5"
    ]
  }
}
